please_debug_my_code/__init__.py
please_debug_my_code-1.0.dist-info/LICENSE
please_debug_my_code-1.0.dist-info/METADATA
please_debug_my_code-1.0.dist-info/WHEEL
please_debug_my_code-1.0.dist-info/top_level.txt
please_debug_my_code-1.0.dist-info/RECORD
