Metadata-Version: 2.1
Name: please-debug-my-code
Version: 1.0
Summary: Perfect debug helper
Home-page: https://github.com/otter18/please_debug_my_code
Author: ChernV (otter18)
Author-email: vchern185@gmail.com
License: UNKNOWN
Platform: UNKNOWN
Classifier: Programming Language :: Python :: 3
Classifier: License :: OSI Approved :: MIT License
Classifier: Operating System :: OS Independent
Requires-Python: >=3
License-File: LICENSE
